LICENSE
README.md
setup.py
vtscan/__init__.py
vtscan/vtscan.py
vtscan.egg-info/PKG-INFO
vtscan.egg-info/SOURCES.txt
vtscan.egg-info/dependency_links.txt
vtscan.egg-info/entry_points.txt
vtscan.egg-info/requires.txt
vtscan.egg-info/top_level.txt