Metadata-Version: 2.1
Name: vtscan
Version: 1.0.20
Summary: Utility to scan for malicious files using the VirusTotal API
Home-page: https://github.com/prahladyeri/vtscan
Author: Prahlad Yeri
Author-email: prahladyeri@yahoo.com
License: MIT
Platform: UNKNOWN
Classifier: Programming Language :: Python :: 3
Classifier: License :: OSI Approved :: MIT License
Classifier: Operating System :: OS Independent
Requires-Python: >= 3.4
